regressionpack/AbstractRegression.py
regressionpack/CosineFit.py
regressionpack/Ellipse.py
regressionpack/Exponential.py
regressionpack/Gaussian.py
regressionpack/GenericCurveFit.py
regressionpack/JonckheereTerpstra.py
regressionpack/Legacy.py
regressionpack/Linear.py
regressionpack/Logistic.py
regressionpack/Polynomial.py
regressionpack/SystemIdentification.py
regressionpack/__init__.py
regressionpack/utilities.py
regressionpack-1.1.1.dist-info/LICENSE.md
regressionpack-1.1.1.dist-info/METADATA
regressionpack-1.1.1.dist-info/WHEEL
regressionpack-1.1.1.dist-info/top_level.txt
regressionpack-1.1.1.dist-info/RECORD
