Metadata-Version: 2.1
Name: regressionpack
Version: 1.1.1
Summary: Library for making regression with errorbars a walk in the park. 
Home-page: https://pypi.org/project/regressionpack/
Author: FusedSilica
Author-email: caronmartin3@gmail.com
License: UNKNOWN
Platform: UNKNOWN
Classifier: Development Status :: 2 - Pre-Alpha
Classifier: Intended Audience :: Education
Classifier: Intended Audience :: Science/Research
Classifier: License :: OSI Approved :: GNU Lesser General Public License v3 (LGPLv3)
Classifier: Operating System :: OS Independent
Classifier: Programming Language :: Python :: 3.7
Classifier: Topic :: Scientific/Engineering :: Mathematics
Requires-Python: >=3.8.3
Requires-Dist: numpy (>=1.21.5)
Requires-Dist: scipy (>=1.7.3)
Requires-Dist: matplotlib (>=3.1)
